grokcore.component-4.2-py3.12-nspkg.pth
grokcore/component/__init__.py
grokcore/component/compat.py
grokcore/component/components.py
grokcore/component/decorators.py
grokcore/component/directive.py
grokcore/component/interfaces.py
grokcore/component/meta.py
grokcore/component/meta.zcml
grokcore/component/subscription.py
grokcore/component/testing.py
grokcore/component/util.py
grokcore/component/zcml.py
grokcore/component/templates/default_display_form.pt
grokcore/component/templates/default_edit_form.pt
grokcore/component/tests/__init__.py
grokcore/component/tests/api.txt
grokcore/component/tests/grok_component.txt
grokcore/component/tests/test_grok.py
grokcore/component/tests/adapter/__init__.py
grokcore/component/tests/adapter/adapter.py
grokcore/component/tests/adapter/adapterdecorator.py
grokcore/component/tests/adapter/alphabetical.py
grokcore/component/tests/adapter/classcontext.py
grokcore/component/tests/adapter/classcontextimported.py
grokcore/component/tests/adapter/classcontextmultiple.py
grokcore/component/tests/adapter/classcontextmultiple_fixture.py
grokcore/component/tests/adapter/classorinterface.py
grokcore/component/tests/adapter/conflict.py
grokcore/component/tests/adapter/functionasargument_fixture.py
grokcore/component/tests/adapter/functioncontext.py
grokcore/component/tests/adapter/globaladapter.py
grokcore/component/tests/adapter/implementsmany.py
grokcore/component/tests/adapter/implementsnone.py
grokcore/component/tests/adapter/implementsnonemulti.py
grokcore/component/tests/adapter/importedmodel.py
grokcore/component/tests/adapter/importedmodel2.py
grokcore/component/tests/adapter/interface.py
grokcore/component/tests/adapter/interfacemodule.py
grokcore/component/tests/adapter/modulecontext.py
grokcore/component/tests/adapter/modulecontextimported.py
grokcore/component/tests/adapter/modulecontextmultiple.py
grokcore/component/tests/adapter/modulecontextmultiple_fixture.py
grokcore/component/tests/adapter/multiadapter.py
grokcore_component-4.2.dist-info/licenses/LICENSE.txt
grokcore_component-4.2.dist-info/METADATA
grokcore_component-4.2.dist-info/WHEEL
grokcore_component-4.2.dist-info/namespace_packages.txt
grokcore_component-4.2.dist-info/top_level.txt
grokcore_component-4.2.dist-info/RECORD
