Metadata-Version: 2.4
Name: grokcore.component
Version: 4.2
Summary: Grok-like configuration for basic components (adapters, utilities, subscribers)
Home-page: https://github.com/zopefoundation/grokcore.component
Author: Grok Team
Author-email: zope-dev@zope.dev
License: ZPL
Classifier: Intended Audience :: Developers
Classifier: Development Status :: 6 - Mature
Classifier: License :: OSI Approved :: Zope Public License
Classifier: Operating System :: OS Independent
Classifier: Programming Language :: Python :: 3
Classifier: Programming Language :: Python :: 3.9
Classifier: Programming Language :: Python :: 3.10
Classifier: Programming Language :: Python :: 3.11
Classifier: Programming Language :: Python :: 3.12
Classifier: Programming Language :: Python :: 3.13
Classifier: Programming Language :: Python :: Implementation :: CPython
Classifier: Programming Language :: Python :: Implementation :: PyPy
Requires-Python: >=3.9
License-File: LICENSE.txt
Requires-Dist: setuptools
Requires-Dist: martian>=1.2
Requires-Dist: zope.component
Requires-Dist: zope.configuration
Requires-Dist: zope.interface
Requires-Dist: zope.testing
Provides-Extra: test
Requires-Dist: zope.event; extra == "test"
Dynamic: author
Dynamic: author-email
Dynamic: classifier
Dynamic: description
Dynamic: home-page
Dynamic: license
Dynamic: license-file
Dynamic: provides-extra
Dynamic: requires-dist
Dynamic: requires-python
Dynamic: summary
